ShockOscillationAnalysis/ShockOscillationAnalysis.py
ShockOscillationAnalysis/__init__.py
ShockOscillationAnalysis/constants.py
ShockOscillationAnalysis/decorators.py
ShockOscillationAnalysis/generateshocksignal.py
ShockOscillationAnalysis/imgcleaningfunctions.py
ShockOscillationAnalysis/linedrawingfunctions.py
ShockOscillationAnalysis/preview.py
ShockOscillationAnalysis/shocktracking.py
ShockOscillationAnalysis/shocktracking_opt.py
ShockOscillationAnalysis/shocktrackingoptimized.py
ShockOscillationAnalysis/support_func.py
ShockOscillationAnalysis/inc_tracking/__init__.py
ShockOscillationAnalysis/inc_tracking/inc_tracking.py
ShockOscillationAnalysis/inc_tracking/inc_tracking_support.py
ShockOscillationAnalysis/inc_tracking/tracking_accuracy.py
ShockOscillationAnalysis/slice_list_generator/__init__.py
ShockOscillationAnalysis/slice_list_generator/list_generation_tools.py
ShockOscillationAnalysis/slice_list_generator/slice_list_generator.py
shockoscillationanalysis-2.15.10.dist-info/licenses/LICENSE
shockoscillationanalysis-2.15.10.dist-info/METADATA
shockoscillationanalysis-2.15.10.dist-info/WHEEL
shockoscillationanalysis-2.15.10.dist-info/top_level.txt
shockoscillationanalysis-2.15.10.dist-info/RECORD
