Metadata-Version: 2.4
Name: ShockOscillationAnalysis
Version: 2.15.10
Home-page: https://github.com/EngAhmedHady/ShockTrackingLibrary
Author: Ahmed H. Hanfy, Pawel Flaszyński, Piotr Kaczyński, Piotr Doerffer
Author-email: ahmed.hady.hanfy92@gmail.com
License: MIT
Requires-Python: >= 3.11
License-File: LICENSE
Requires-Dist: opencv-python>=4.10.0
Requires-Dist: numpy>=2.1.2
Requires-Dist: scipy>=1.11.4
Requires-Dist: matplotlib>=3.8.0
Requires-Dist: Pillow>=10.3.0
Requires-Dist: datetime
Requires-Dist: screeninfo
Requires-Dist: keyboard
Dynamic: author
Dynamic: author-email
Dynamic: description
Dynamic: description-content-type
Dynamic: home-page
Dynamic: license
Dynamic: license-file
Dynamic: requires-dist
Dynamic: requires-python
